{"title":"Gallery","markdown":{"yaml":{"title":"Gallery","title-block-banner":true,"comments":false},"containsRefs":false,"markdown":"\n\n{{< fa hammer >}} Under construction...\n\nIf you are interested in any of images from this gallery or my [instagram account](https://www.instagram.com/danielsangarci_wildlife/?hl=es), please [contact me](contact.qmd).\n\n::: {layout-ncol=\"3\"}\n![](img/messor_structor_small.jpg)\n\n![](img/bee1_small.jpg)\n\n![](img/caterpillar_small.jpg)\n\n![](img/ephem1_small.jpg)\n\n![](img/grasshopper_small.jpg)\n\n![](img/lasius_grandis_small.jpg)\n\n![](img/mantis1_small.jpg)\n\n![](img/snail1_small.jpg)\n\n![](img/solenopsis1_small.jpg)\n\n![](img/spider1_small.jpg)\n\n![](img/spider2_small.jpg)\n\n![](img/spider3_small.jpg)\n\n![](img/formica1_small.jpg)\n\n![](img/macu1_small.jpg)\n\n![](img/macu2_small.jpg)\n:::\n"},"formats":{"html":{"execute":{"fig-width":7,"fig-height":5,"fig-format":"retina","fig-dpi":96,"df-print":"default","error":false,"eval":true,"cache":null,"freeze":false,"echo":true,"output":true,"warning":true,"include":true,"keep-md":false,"keep-ipynb":false,"ipynb":null,"enabled":null,"daemon":null,"daemon-restart":false,"debug":false,"ipynb-filters":[],"engine":"markdown"},"render":{"keep-tex":false,"keep-source":false,"keep-hidden":false,"prefer-html":false,"output-divs":true,"output-ext":"html","fig-align":"default","fig-pos":null,"fig-env":null,"code-fold":"none","code-overflow":"scroll","code-link":false,"code-line-numbers":false,"code-tools":false,"tbl-colwidths":"auto","merge-includes":true,"latex-auto-mk":true,"latex-auto-install":true,"latex-clean":true,"latex-max-runs":10,"latex-makeindex":"makeindex","latex-makeindex-opts":[],"latex-tlmgr-opts":[],"latex-input-paths":[],"latex-output-dir":null,"link-external-icon":false,"link-external-newwindow":false,"self-contained-math":false,"format-resources":[]},"pandoc":{"standalone":true,"wrap":"none","default-image-extension":"png","to":"html","css":["styles.css"],"toc":true,"output-file":"gallery.html"},"language":{},"metadata":{"lang":"en","fig-responsive":true,"quarto-version":"1.2.335","editor":"visual","theme":{"light":"cosmo","dark":"cosmo"},"fontsize":"1.3em","linestretch":1.7,"page-layout":"full","linkcolor":"#88A7C2","title":"Gallery","title-block-banner":true,"comments":false},"extensions":{"book":{"multiFile":true}}}}}